{"matic":{"id":137,"name":"Polygon","nativeCurrency":{"name":"MATIC","symbol":"MATIC","decimals":18},"blockExplorers":{"default":{"name":"PolygonScan","url":"https://polygonscan.com","apiUrl":"https://api.polygonscan.com/api"}}},"celo":{"id":42220,"name":"Celo","nativeCurrency":{"decimals":18,"name":"CELO","symbol":"CELO"},"blockExplorers":{"default":{"name":"Celo Explorer","url":"https://celoscan.io","apiUrl":"https://api.celoscan.io/api"}}},"cro":{"id":25,"name":"Cronos Mainnet","nativeCurrency":{"decimals":18,"name":"Cronos","symbol":"CRO"},"blockExplorers":{"default":{"name":"Cronos Explorer","url":"https://explorer.cronos.org","apiUrl":"https://explorer-api.cronos.org/mainnet/api"}}},"etc":{"id":61,"name":"Ethereum Classic","nativeCurrency":{"decimals":18,"name":"ETC","symbol":"ETC"},"blockExplorers":{"default":{"name":"Blockscout","url":"https://blockscout.com/etc/mainnet"}}},"ftm":{"id":250,"name":"Fantom","nativeCurrency":{"decimals":18,"name":"Fantom","symbol":"FTM"},"blockExplorers":{"default":{"name":"FTMScan","url":"https://ftmscan.com","apiUrl":"https://api.ftmscan.com/api"}}},"gno":{"id":100,"name":"Gnosis","nativeCurrency":{"decimals":18,"name":"Gnosis","symbol":"xDAI"},"blockExplorers":{"default":{"name":"Gnosisscan","url":"https://gnosisscan.io","apiUrl":"https://api.gnosisscan.io/api"}}},"op":{"id":10,"name":"OP Mainnet","nativeCurrency":{"name":"Ether","symbol":"ETH","decimals":18},"blockExplorers":{"default":{"name":"Optimism Explorer","url":"https://optimistic.etherscan.io","apiUrl":"https://api-optimistic.etherscan.io/api"}}},"arb1":{"id":42161,"name":"Arbitrum One","nativeCurrency":{"name":"Ether","symbol":"ETH","decimals":18},"blockExplorers":{"default":{"name":"Arbiscan","url":"https://arbiscan.io","apiUrl":"https://api.arbiscan.io/api"}}},"base":{"id":8453,"name":"Base","nativeCurrency":{"name":"Ether","symbol":"ETH","decimals":18},"blockExplorers":{"default":{"name":"Basescan","url":"https://basescan.org","apiUrl":"https://api.basescan.org/api"}}},"linea":{"id":59144,"name":"Linea Mainnet","nativeCurrency":{"name":"Linea Ether","symbol":"ETH","decimals":18},"blockExplorers":{"default":{"name":"Etherscan","url":"https://lineascan.build","apiUrl":"https://api.lineascan.build/api"}}},"zora":{"id":7777777,"name":"Zora","nativeCurrency":{"decimals":18,"name":"Ether","symbol":"ETH"},"blockExplorers":{"default":{"name":"Explorer","url":"https://explorer.zora.energy","apiUrl":"https://explorer.zora.energy/api"}}},"zksync":{"id":324,"name":"ZKsync Era","nativeCurrency":{"decimals":18,"name":"Ether","symbol":"ETH"},"blockExplorers":{"default":{"name":"Etherscan","url":"https://era.zksync.network/","apiUrl":"https://api-era.zksync.network/api"},"native":{"name":"ZKsync Explorer","url":"https://explorer.zksync.io/","apiUrl":"https://block-explorer-api.mainnet.zksync.io/api"}}},"metis":{"id":1088,"name":"Metis","nativeCurrency":{"decimals":18,"name":"Metis","symbol":"METIS"},"blockExplorers":{"default":{"name":"Metis Explorer","url":"https://explorer.metis.io","apiUrl":"https://api.routescan.io/v2/network/mainnet/evm/43114/etherscan/api"},"blockscout":{"name":"Andromeda Explorer","url":"https://andromeda-explorer.metis.io","apiUrl":"https://andromeda-explorer.metis.io/api"}}},"avaxc":{"id":43114,"name":"Avalanche","nativeCurrency":{"decimals":18,"name":"Avalanche","symbol":"AVAX"},"blockExplorers":{"default":{"name":"SnowTrace","url":"https://snowtrace.io","apiUrl":"https://api.snowtrace.io"}}},"bsc":{"id":56,"name":"BNB Smart Chain","nativeCurrency":{"decimals":18,"name":"BNB","symbol":"BNB"},"blockExplorers":{"default":{"name":"BscScan","url":"https://bscscan.com","apiUrl":"https://api.bscscan.com/api"}}},"scr":{"id":534352,"name":"Scroll Mainnet","nativeCurrency":{"name":"Ether","symbol":"ETH","decimals":18},"blockExplorers":{"default":{"name":"Scrollscan","url":"https://scrollscan.com","apiUrl":"https://api.scrollscan.com/api"}}}}
